odoo10_addon_partner_event-10.0.2.1.1-nspkg.pth
odoo/addons/partner_event/README.rst
odoo/addons/partner_event/__init__.py
odoo/addons/partner_event/__manifest__.py
odoo/addons/partner_event/hooks.py
odoo/addons/partner_event/i18n/es.po
odoo/addons/partner_event/i18n/partner_event.pot
odoo/addons/partner_event/i18n/sl.po
odoo/addons/partner_event/migrations/10.0.2.0.0/post-migration.py
odoo/addons/partner_event/migrations/10.0.2.1.0/post-migrate.py
odoo/addons/partner_event/models/__init__.py
odoo/addons/partner_event/models/event_event.py
odoo/addons/partner_event/models/event_registration.py
odoo/addons/partner_event/models/res_partner.py
odoo/addons/partner_event/static/description/icon.png
odoo/addons/partner_event/tests/__init__.py
odoo/addons/partner_event/tests/test_event_registration.py
odoo/addons/partner_event/views/event_event_view.xml
odoo/addons/partner_event/views/event_registration_view.xml
odoo/addons/partner_event/views/res_partner_view.xml
odoo/addons/partner_event/wizard/__init__.py
odoo/addons/partner_event/wizard/res_partner_register_event.py
odoo/addons/partner_event/wizard/res_partner_register_event_view.xml
odoo10_addon_partner_event-10.0.2.1.1.dist-info/METADATA
odoo10_addon_partner_event-10.0.2.1.1.dist-info/WHEEL
odoo10_addon_partner_event-10.0.2.1.1.dist-info/namespace_packages.txt
odoo10_addon_partner_event-10.0.2.1.1.dist-info/top_level.txt
odoo10_addon_partner_event-10.0.2.1.1.dist-info/RECORD
